{
    "cliente_dni": "98789787",
    "cliente_apellido": "Bardales",
    "cliente_nombre": "Rodriguez",
    "cliente_direccion": "Peru, lambayeque",
    "cliente_telefono": "98787687676",
    "producto_cod_1": "aua",
    "producto_cod_2": "aeu",
    "producto_cod_3": "aoe",
    "producto_desc_2": "Tarugos PVC",
    "producto_desc_3": "Tarugos de Nylon",
    "producto_unit_1": "Caja x500 unidades",
    "producto_unit_2": "Caja x100 unidades",
    "producto_unit_3": "Caja x100 unidades",
    "producto_cant_1": "2",
    "producto_cant_2": "2",
    "producto_cant_3": "2",
    "producto_precio_1": "81.90",
    "producto_precio_2": "8.20",
    "producto_precio_3": "24.90",
    "producto_subtotal_1": "163.8",
    "producto_subtotal_2": "16.4",
    "producto_subtotal_3": "49.8",
    "producto_total": "271.4"
}